amp_instrumentation/__init__.py
amp_instrumentation/_bootstrap/__init__.py
amp_instrumentation/_bootstrap/constants.py
amp_instrumentation/_bootstrap/initialization.py
amp_instrumentation/_bootstrap/sitecustomize.py
amp_instrumentation/_bootstrap/utils.py
amp_instrumentation/cli/__init__.py
amp_instrumentation/cli/main.py
amp_instrumentation-0.1.2.dist-info/METADATA
amp_instrumentation-0.1.2.dist-info/WHEEL
amp_instrumentation-0.1.2.dist-info/entry_points.txt
amp_instrumentation-0.1.2.dist-info/licenses/LICENSE
amp_instrumentation-0.1.2.dist-info/RECORD
