Metadata-Version: 2.4
Name: amp-instrumentation
Version: 0.1.2
Summary: Automatic instrumentation for Python agent applications, monitored via WSO2 Agent Management Platform
Project-URL: Repository, https://github.com/wso2/ai-agent-management-platform
Author-email: WSO2 <hansi@wso2.org>
Maintainer-email: WSO2 <hansi@wso2.org>
License: Apache-2.0
License-File: LICENSE
Requires-Python: >=3.10
Requires-Dist: traceloop-sdk>=0.47.0
